altair_recipes/__init__.py
altair_recipes/areaplot.py
altair_recipes/autocorrelation.py
altair_recipes/autoplot.py
altair_recipes/barchart.py
altair_recipes/boxplot.py
altair_recipes/common.py
altair_recipes/converters.py
altair_recipes/display_pweave.py
altair_recipes/heatmap.py
altair_recipes/histogram.py
altair_recipes/lineplot.py
altair_recipes/qqplot.py
altair_recipes/scatterplot.py
altair_recipes/signatures.py
altair_recipes/smoother.py
altair_recipes/stripplot.py
altair_recipes-0.9.2.dist-info/LICENSE
altair_recipes-0.9.2.dist-info/WHEEL
altair_recipes-0.9.2.dist-info/METADATA
altair_recipes-0.9.2.dist-info/RECORD
