Metadata-Version: 2.1
Name: altair-recipes
Version: 0.9.2
Summary: A collection of ready-made statistical graphics for vega
Home-page: https://github.com/piccolbo/altair_recipes
License: GPL-3.0
Author: Antonio Piccolboni
Author-email: antonio@piccolboni.info
Requires-Python: >=3.8.0,<4.0.0
Classifier: Development Status :: 4 - Beta
Classifier: Intended Audience :: Developers
Classifier: License :: OSI Approved :: GNU General Public License v3 (GPLv3)
Classifier: Programming Language :: Python :: 3
Classifier: Programming Language :: Python :: 3.10
Classifier: Programming Language :: Python :: 3.8
Classifier: Programming Language :: Python :: 3.9
Provides-Extra: pweave
Requires-Dist: altair (>=4.0.0,<5.0.0)
Requires-Dist: attrs (>=19.2,<20.0)
Requires-Dist: autosig (>=0.10.0)
Requires-Dist: boltons (>=19.1.0)
Requires-Dist: ipython (>=7.16.3,<8.0.0); extra == "pweave"
Requires-Dist: numpy (>=1.17.0)
Requires-Dist: pandas (>=0.25.0)
Requires-Dist: requests (>=2.22.0)
Requires-Dist: toolz (>=0.10.0)
Project-URL: Documentation, https://altair_recipes.readthedocs.io/en/latest/
Project-URL: Repository, https://github.com/piccolbo/altair_recipes
